pypiserver_passlib/__init__.py
pypiserver_passlib/_version.py
pypiserver_passlib/auth.py
pypiserver_passlib-1.0.0.dev2.dist-info/METADATA
pypiserver_passlib-1.0.0.dev2.dist-info/RECORD
pypiserver_passlib-1.0.0.dev2.dist-info/WHEEL
pypiserver_passlib-1.0.0.dev2.dist-info/entry_points.txt
pypiserver_passlib-1.0.0.dev2.dist-info/top_level.txt
